effspm/__init__.py
effspm/load_inst.hpp
effspm/_core.cpp
effspm/_effspm.cpp
effspm/_effspm.cpython-312-x86_64-linux-gnu.so
effspm/load_inst.cpp
effspm/freq_miner.hpp
effspm/freq_miner.cpp
effspm/utility.cpp
effspm/utility.hpp
effspm/main.cpp
effspm/largebm/src/load_inst.hpp
effspm/largebm/src/build_mdd.cpp
effspm/largebm/src/load_inst.cpp
effspm/largebm/src/freq_miner.hpp
effspm/largebm/src/freq_miner.cpp
effspm/largebm/src/utility.cpp
effspm/largebm/src/utility.hpp
effspm/largebm/src/main.cpp
effspm/largebm/src/build_mdd.hpp
effspm/largepp/src/load_inst.hpp
effspm/largepp/src/load_inst.cpp
effspm/largepp/src/freq_miner.hpp
effspm/largepp/src/freq_miner.cpp
effspm/largepp/src/pattern.hpp
effspm/largepp/src/utility.cpp
effspm/largepp/src/utility.hpp
effspm/largepp/src/main.cpp
effspm/btminer/src/load_inst.hpp
effspm/btminer/src/build_mdd.cpp
effspm/btminer/src/load_inst.cpp
effspm/btminer/src/freq_miner.hpp
effspm/btminer/src/freq_miner.cpp
effspm/btminer/src/utility.cpp
effspm/btminer/src/utility.hpp
effspm/btminer/src/main.cpp
effspm/btminer/src/build_mdd.hpp
effspm/largehm/src/load_inst.hpp
effspm/largehm/src/build_mdd.cpp
effspm/largehm/src/load_inst.cpp
effspm/largehm/src/freq_miner.hpp
effspm/largehm/src/freq_miner.cpp
effspm/largehm/src/utility.cpp
effspm/largehm/src/utility.hpp
effspm/largehm/src/main.cpp
effspm/largehm/src/build_mdd.hpp
effspm/htminer/src/load_inst.hpp
effspm/htminer/src/build_mdd.cpp
effspm/htminer/src/load_inst.cpp
effspm/htminer/src/freq_miner.hpp
effspm/htminer/src/freq_miner.cpp
effspm/htminer/src/utility.cpp
effspm/htminer/src/utility.hpp
effspm/htminer/src/main.cpp
effspm/htminer/src/build_mdd.hpp
effspm-0.3.3.dist-info/top_level.txt
effspm-0.3.3.dist-info/WHEEL
effspm-0.3.3.dist-info/RECORD
effspm-0.3.3.dist-info/METADATA
effspm-0.3.3.dist-info/licenses/LICENSE
