Metadata-Version: 2.4
Name: effspm
Version: 0.3.3
Summary: Prefix‑Projection and other sequential pattern mining algorithms
Author: Yeswanth Vootla
Author-email: yeshu999 <vootlayeswanth20@gmail.com>
License:                                  Apache License
Project-URL: Homepage, https://github.com/yeshu999/effspm
Project-URL: Source, https://github.com/yeshu999/effspm
Classifier: Programming Language :: Python :: 3.7
Classifier: Programming Language :: Python :: 3.8
Classifier: Programming Language :: Python :: 3.9
Classifier: Programming Language :: Python :: 3.10
Classifier: Programming Language :: Python :: 3.11
Classifier: Programming Language :: Python :: 3.12
Classifier: Programming Language :: Python :: 3.13
Classifier: Programming Language :: C++
Classifier: License :: OSI Approved :: MIT License
Classifier: Operating System :: OS Independent
Requires-Python: >=3.7
License-File: LICENSE
Requires-Dist: pybind11>=2.6
Dynamic: author
Dynamic: license-file
